Metadata-Version: 1.0
Name: megazord
Version: 0.1.1
Summary: SoftNext DeepL Project
Home-page: https://github.com/iSab01/megazord
Author: Lucas Saban
Author-email: lucas.saban@ensae.fr
License: Sofnext
Platform: UNKNOWN
